cx_Oracle_async/AQ.py
cx_Oracle_async/__init__.py
cx_Oracle_async/connections.py
cx_Oracle_async/context.py
cx_Oracle_async/cursors.py
cx_Oracle_async/pools.py
cx_Oracle_async/utils.py
cx_Oracle_async-0.3.3.dist-info/LICENSE
cx_Oracle_async-0.3.3.dist-info/METADATA
cx_Oracle_async-0.3.3.dist-info/WHEEL
cx_Oracle_async-0.3.3.dist-info/top_level.txt
cx_Oracle_async-0.3.3.dist-info/RECORD
