Metadata-Version: 2.1
Name: cx-Oracle-async
Version: 0.3.3
Summary: A very simple asynchronous wrapper that allows you to get access to the Oracle database in asyncio programs.
Home-page: https://github.com/GoodManWEN/cx_Oracle_async
Author: WEN
License: UNKNOWN
Keywords: oracle,cx_Oracle,asyncio,cx_Oracle_async
Platform: UNKNOWN
Classifier: Programming Language :: Python :: 3
Classifier: Programming Language :: Python :: 3.7
Classifier: Programming Language :: Python :: 3.8
Classifier: Programming Language :: Python :: 3.9
Classifier: License :: OSI Approved :: MIT License
Classifier: Operating System :: POSIX :: Linux
Classifier: Operating System :: Microsoft :: Windows
Classifier: Framework :: AsyncIO
Requires-Python: >=3.7
Requires-Dist: cx-Oracle (>=8.1.0)
Requires-Dist: ThreadPoolExecutorPlus (>=0.2.0)
